src/app.py
src/cli.py
genaikit/__init__.py
genaikit/__main__.py
genaikit/async_base.py
genaikit/async_core.py
genaikit/base.py
genaikit/constants.py
genaikit/core.py
genaikit/errors.py
genaikit/extractors/__init__.py
genaikit/extractors/base.py
genaikit/extractors/pdf.py
genaikit/nlp/__init__.py
genaikit/nlp/base.py
genaikit/nlp/processors.py
genaikit/prompts.py
genaikit/settings.py
genaikit/utils.py
src/gui.py
genaikit-1.4.0.dist-info/METADATA
genaikit-1.4.0.dist-info/WHEEL
genaikit-1.4.0.dist-info/entry_points.txt
genaikit-1.4.0.dist-info/RECORD
