Metadata-Version: 2.1
Name: genaikit
Version: 1.4.0
Summary: AI code and general assistant powered by OpenAI
License: None
Author: Vagner Bessa
Author-email: bessavagner@gmail.com
Requires-Python: >=3.10.12,<3.13
Classifier: License :: Other/Proprietary License
Classifier: Programming Language :: Python :: 3
Classifier: Programming Language :: Python :: 3.11
Classifier: Programming Language :: Python :: 3.12
Requires-Dist: openai (>=1.3.4,<2.0.0)
Requires-Dist: pandas (>=2.1.3,<3.0.0)
Requires-Dist: pyarrow (==12.0.1)
Requires-Dist: python-dotenv (>=1.0.0,<2.0.0)
Requires-Dist: scipy (>=1.11.4,<2.0.0)
Requires-Dist: spacy (>=3.7.2,<4.0.0)
Requires-Dist: tiktoken (>=0.5.1,<0.6.0)
